BeamDelta/BeamDeltaUI.py
BeamDelta/__init__.py
BeamDelta-1.1.0.dist-info/COPYING
BeamDelta-1.1.0.dist-info/METADATA
BeamDelta-1.1.0.dist-info/WHEEL
BeamDelta-1.1.0.dist-info/entry_points.txt
BeamDelta-1.1.0.dist-info/top_level.txt
BeamDelta-1.1.0.dist-info/RECORD
