Metadata-Version: 2.1
Name: BeamDelta
Version: 1.1.0
Summary: A software tool to improve microscope alignment
Home-page: https://github.com/MicronOxford/BeamDelta
Author: See homepage for a complete list of contributors
Author-email: 
License: UNKNOWN
Platform: UNKNOWN
Classifier: Intended Audience :: Science/Research
Classifier: Topic :: Scientific/Engineering
Classifier: License :: OSI Approved :: GNU General Public License v3 or later (GPLv3+)
Requires-Python: >=3.5
Requires-Dist: PyQt5
Requires-Dist: scikit-image
Requires-Dist: scipy
Requires-Dist: microscope
